README.rst
setup.py
qeds/__init__.py
qeds/themes.py
qeds/version.py
qeds.egg-info/PKG-INFO
qeds.egg-info/SOURCES.txt
qeds.egg-info/dependency_links.txt
qeds.egg-info/requires.txt
qeds.egg-info/top_level.txt
qeds/data/__init__.py
qeds/data/config.py
qeds/data/loader.py
qeds/data/retrievers.py
qeds/data/shopify.py
qeds/data/util.py
qeds/data/bls/__init__.py
qeds/data/bls/core.py
qeds/data/bls/util.py
qeds/data/socrata/__init__.py
qeds/data/socrata/core.py
qeds/data/socrata/util.py
qeds/data/uscensus/__init__.py
qeds/data/uscensus/core.py
qeds/data/uscensus/util.py